opencv_cam_idx/__init__.py
opencv_cam_idx/finder.py
opencv_cam_idx/moniker.py
opencv_cam_idx/py.typed
opencv_cam_idx-1.0.1.dist-info/LICENSE
opencv_cam_idx-1.0.1.dist-info/METADATA
opencv_cam_idx-1.0.1.dist-info/WHEEL
opencv_cam_idx-1.0.1.dist-info/top_level.txt
opencv_cam_idx-1.0.1.dist-info/RECORD
