Metadata-Version: 2.1
Name: opencv-cam-idx
Version: 1.0.1
Summary: Find opencv camera index in windows using win32 api
Author-email: Pradish Bijukchhe <pradish@sandbox.com.np>
License: Copyright (c) 2018 The Python Packaging Authority
Project-URL: Homepage, https://github.com/sandbox-pokhara/opencv-cam-idx
Project-URL: Issues, https://github.com/sandbox-pokhara/opencv-cam-idx/issues
Classifier: Programming Language :: Python :: 3
Requires-Python: >=3
License-File: LICENSE
Requires-Dist: comtypes
